[{"key": "我<br>", "original": "我<br>", "translation": ""}, {"key": "我到这儿了！而且门也没锁！", "original": "我到这儿了！而且门也没锁！", "translation": ""}, {"key": "再坚持一下！！", "original": "再坚持一下！！", "translation": ""}, {"key": "\\C[14]埃米小姐\\C[0] <br>", "original": "\\C[14]埃米小姐\\C[0] <br>", "translation": ""}, {"key": "\\n[1]！你在这干什么？？", "original": "\\n[1]！你在这干什么？？", "translation": ""}, {"key": "呃呃...", "original": "呃呃...", "translation": ""}, {"key": "抱歉，\\C[14]埃米小姐\\C[0]! <br>", "original": "抱歉，\\C[14]埃米小姐\\C[0]! <br>", "translation": ""}, {"key": "我现在有点情况，所以最好先躲在这里...", "original": "我现在有点情况，所以最好先躲在这里...", "translation": ""}, {"key": "你有什么情-", "original": "你有什么情-", "translation": ""}, {"key": "我去...", "original": "我去...", "translation": ""}, {"key": "你能不能像之前那样帮我解决一下...？", "original": "你能不能像之前那样帮我解决一下...？", "translation": ""}, {"key": "\\n[1]！我们不能这么做！<br>", "original": "\\n[1]！我们不能这么做！<br>", "translation": ""}, {"key": "尤其在这种地方更不行！", "original": "尤其在这种地方更不行！", "translation": ""}, {"key": "（等等！<br>", "original": "（等等！<br>", "translation": ""}, {"key": "\\n[1]上次丢在我桌上那本书里教的技巧叫什么来着...）", "original": "\\n[1]上次丢在我桌上那本书里教的技巧叫什么来着...）", "translation": ""}, {"key": "（那种能立刻让他射出来的技巧...<br>", "original": "（那种能立刻让他射出来的技巧...<br>", "translation": ""}, {"key": "叫什么来着？<br>", "original": "叫什么来着？<br>", "translation": ""}, {"key": "高速旋转攻三点？）", "original": "高速旋转攻三点？）", "translation": ""}, {"key": "（嗯...）", "original": "（嗯...）", "translation": ""}, {"key": "这样吧，我想到个好主意！", "original": "这样吧，我想到个好主意！", "translation": ""}, {"key": "你保证不会告诉其他人！", "original": "你保证不会告诉其他人！", "translation": ""}, {"key": "那肯定的，<br>", "original": "那肯定的，<br>", "translation": ""}, {"key": "我连你想说什么都不知道，当然不会告诉别人了", "original": "我连你想说什么都不知道，当然不会告诉别人了", "translation": ""}, {"key": "那当然！！！", "original": "那当然！！！", "translation": ""}, {"key": "跟我来...", "original": "跟我来...", "translation": ""}, {"key": "快进去！", "original": "快进去！", "translation": ""}, {"key": "好！", "original": "好！", "translation": ""}, {"key": "哇哦，这感觉好奇妙，\\C[14]埃米小姐\\C[0]!", "original": "哇哦，这感觉好奇妙，\\C[14]埃米小姐\\C[0]!", "translation": ""}, {"key": "我还从来没经历过这种场面！", "original": "我还从来没经历过这种场面！", "translation": ""}, {"key": "（哇哦！这是什么感觉？！<br>", "original": "（哇哦！这是什么感觉？！<br>", "translation": ""}, {"key": "好软...）", "original": "好软...）", "translation": ""}, {"key": "（(\\C[14]埃米小姐\\C[0]离我好近<br>", "original": "（(\\C[14]埃米小姐\\C[0]离我好近<br>", "translation": ""}, {"key": "我都能闻到她身上的香味）", "original": "我都能闻到她身上的香味）", "translation": ""}, {"key": "还有什么比这更舒服的？？", "original": "还有什么比这更舒服的？？", "translation": ""}, {"key": "嘘，\\n[1]！让我集中注意力", "original": "嘘，\\n[1]！让我集中注意力", "translation": ""}, {"key": "哦好！", "original": "哦好！", "translation": ""}, {"key": "（这是什么大小啊...<br>", "original": "（这是什么大小啊...<br>", "translation": ""}, {"key": "真是太大了，不知道我的下巴撑不撑得住...）", "original": "真是太大了，不知道我的下巴撑不撑得住...）", "translation": ""}, {"key": "（希望我没做错什么步骤）", "original": "（希望我没做错什么步骤）", "translation": ""}, {"key": "哇哦，还真的更舒服了！", "original": "哇哦，还真的更舒服了！", "translation": ""}, {"key": "小点声！别被别人听见了...", "original": "小点声！别被别人听见了...", "translation": ""}, {"key": "对对...", "original": "对对...", "translation": ""}, {"key": "更快点", "original": "更快点", "translation": ""}, {"key": "（他的鸡巴变得好热...<br>", "original": "（他的鸡巴变得好热...<br>", "translation": ""}, {"key": "感觉我嘴都烧起来了...）", "original": "感觉我嘴都烧起来了...）", "translation": ""}, {"key": "感觉舒服吗，\\n[1]?", "original": "感觉舒服吗，\\n[1]?", "translation": ""}, {"key": "嗯... \\C[14]埃米小姐\\C[0]!", "original": "嗯... \\C[14]埃米小姐\\C[0]!", "translation": ""}, {"key": "哈啊...<br>", "original": "哈啊...<br>", "translation": ""}, {"key": "你的小嘴好软好滑...", "original": "你的小嘴好软好滑...", "translation": ""}, {"key": "我能感到你的小舌头每次蹭着我的龟头的感觉<br>", "original": "我能感到你的小舌头每次蹭着我的龟头的感觉<br>", "translation": ""}, {"key": "感觉好神奇...", "original": "感觉好神奇...", "translation": ""}, {"key": "射精", "original": "射精", "translation": ""}, {"key": "我感觉快要出来了，\\C[14]埃米小姐\\C[0]!!!", "original": "我感觉快要出来了，\\C[14]埃米小姐\\C[0]!!!", "translation": ""}, {"key": "（它变得好烫，还一颤一颤的<br>", "original": "（它变得好烫，还一颤一颤的<br>", "translation": ""}, {"key": "他是要射了吗！？）", "original": "他是要射了吗！？）", "translation": ""}, {"key": "要出来了！！", "original": "要出来了！！", "translation": ""}, {"key": "哈啊...哈啊...", "original": "哈啊...哈啊...", "translation": ""}, {"key": "（呃啊！这是什么量？）", "original": "（呃啊！这是什么量？）", "translation": ""}, {"key": "（他射了好多...）", "original": "（他射了好多...）", "translation": ""}, {"key": "（我满脑子都是这种味道<br>", "original": "（我满脑子都是这种味道<br>", "translation": ""}, {"key": "光含着我亲爱学生的鸡巴<br>就让我的小内裤都湿透了...）", "original": "光含着我亲爱学生的鸡巴<br>就让我的小内裤都湿透了...）", "translation": ""}, {"key": "（！！！）", "original": "（！！！）", "translation": ""}, {"key": "（老天！！我在想什么！？）", "original": "（老天！！我在想什么！？）", "translation": ""}, {"key": "（都怪他给我看的那本小黄书...）", "original": "（都怪他给我看的那本小黄书...）", "translation": ""}, {"key": "你没事吧，\\C[14]埃米小姐\\C[0]?", "original": "你没事吧，\\C[14]埃米小姐\\C[0]?", "translation": ""}, {"key": "\\n[1]你该走了，别让别人看到你！", "original": "\\n[1]你该走了，别让别人看到你！", "translation": ""}, {"key": "没问题！<br>", "original": "没问题！<br>", "translation": ""}, {"key": "谢谢你，\\C[14]埃米小姐\\C[0]!", "original": "谢谢你，\\C[14]埃米小姐\\C[0]!", "translation": ""}, {"key": "（我的天！<br>", "original": "（我的天！<br>", "translation": ""}, {"key": "为什么我...好像在享受做这种事...）", "original": "为什么我...好像在享受做这种事...）", "translation": ""}, {"key": "（我还是能感觉到我学生的鸡吧在我嘴里的形状）", "original": "（我还是能感觉到我学生的鸡吧在我嘴里的形状）", "translation": ""}, {"key": "结束", "original": "结束", "translation": ""}, {"key": "\\C[14]埃米小姐\\C[0]：\\C[3]+5\\C[0]<br>", "original": "\\C[14]埃米小姐\\C[0]：\\C[3]+5\\C[0]<br>", "translation": ""}, {"key": "\\C[14]埃米小姐\\C[0]: \\v[83]", "original": "\\C[14]埃米小姐\\C[0]: \\v[83]", "translation": ""}, {"key": "\\C[14]埃米小姐\\C[0]: \\C[3]+3\\C[0] <br>", "original": "\\C[14]埃米小姐\\C[0]: \\C[3]+3\\C[0] <br>", "translation": ""}, {"key": "\\C[6]贝蒂小姐\\C[0] <br>", "original": "\\C[6]贝蒂小姐\\C[0] <br>", "translation": ""}, {"key": "停下！！", "original": "停下！！", "translation": ""}, {"key": "你在这儿干什么？！", "original": "你在这儿干什么？！", "translation": ""}, {"key": "\\C[6]贝蒂小姐\\C[0]!!!", "original": "\\C[6]贝蒂小姐\\C[0]!!!", "translation": ""}, {"key": "出什么事了，\\C[6]贝蒂\\C[0]!?", "original": "出什么事了，\\C[6]贝蒂\\C[0]!?", "translation": ""}, {"key": "出来看看你的好学生在做什么", "original": "出来看看你的好学生在做什么", "translation": ""}, {"key": "\\n[1]！你在这儿干什么？", "original": "\\n[1]！你在这儿干什么？", "translation": ""}, {"key": "早上好，\\C[14]埃米小姐\\C[0]和\\C[6]贝蒂小姐\\C[0]...", "original": "早上好，\\C[14]埃米小姐\\C[0]和\\C[6]贝蒂小姐\\C[0]...", "translation": ""}, {"key": "我-我真的很想上厕所，<br>我以为这里没人，所以..", "original": "我-我真的很想上厕所，<br>我以为这里没人，所以..", "translation": ""}, {"key": "没事的，下次别这么做了", "original": "没事的，下次别这么做了", "translation": ""}, {"key": "抱歉，\\C[14]埃米小姐\\C[0]！", "original": "抱歉，\\C[14]埃米小姐\\C[0]！", "translation": ""}, {"key": "你真是好对付，\\C[14]埃米\\C[0]！", "original": "你真是好对付，\\C[14]埃米\\C[0]！", "translation": ""}, {"key": "你这就信了这个小滑头说的话？！", "original": "你这就信了这个小滑头说的话？！", "translation": ""}, {"key": "别闹了，\\C[6]贝蒂\\C[0]! <br>", "original": "别闹了，\\C[6]贝蒂\\C[0]! <br>", "translation": ""}, {"key": "这不是什么大不了的事，他没在做什么坏事", "original": "这不是什么大不了的事，他没在做什么坏事", "translation": ""}, {"key": "（这可不好玩！）", "original": "（这可不好玩！）", "translation": ""}, {"key": "你说你真的很想上厕所是吧？", "original": "你说你真的很想上厕所是吧？", "translation": ""}, {"key": "嗯-嗯！", "original": "嗯-嗯！", "translation": ""}, {"key": "现在就上，赶快！", "original": "现在就上，赶快！", "translation": ""}, {"key": "她在开玩笑，不用这样的", "original": "她在开玩笑，不用这样的", "translation": ""}, {"key": "（嗯！！下次我一定能抓住他的小尾巴！）", "original": "（嗯！！下次我一定能抓住他的小尾巴！）", "translation": ""}, {"key": "（\\C[6]贝蒂小姐\\C[0]可能在里面", "original": "（\\C[6]贝蒂小姐\\C[0]可能在里面", "translation": ""}, {"key": "希望我能看一眼...）", "original": "希望我能看一眼...）", "translation": ""}]